LICENSE
MANIFEST.in
README.md
setup.cfg
setup.py
playground_data.egg-info/PKG-INFO
playground_data.egg-info/SOURCES.txt
playground_data.egg-info/dependency_links.txt
playground_data.egg-info/requires.txt
playground_data.egg-info/top_level.txt
plygdata/__init__.py
plygdata/_version.py
plygdata/datacolor.py
plygdata/datahelper.py
plygdata/dataset.py
plygdata/heatmap.py
plygdata/playground.py
plygdata/scalelinear.py
plygdata/state.py