Metadata-Version: 2.1
Name: playground-data
Version: 1.0.0
Summary: Data Generation for Neural Network Playground of Deep Insider
Home-page: https://github.com/DeepInsider/playground-data
Author: Digital Advantage Co., Ltd.
License: Apache License 2.0
Project-URL: Bug Reports, https://github.com/DeepInsider/playground-data/issues
Project-URL: Source, https://github.com/DeepInsider/playground-data/
Project-URL: Playground Deep Insider version, https://re.deepinsider.jp/playground/index.html
Project-URL: Playground Original version, http://playground.tensorflow.org/
Keywords: data generation tensorflow deep neural network playground
Platform: UNKNOWN
Classifier: Development Status :: 4 - Beta
Classifier: Intended Audience :: Developers
Classifier: Intended Audience :: Science/Research
Classifier: Topic :: Scientific/Engineering
Classifier: Topic :: Software Development
Classifier: License :: OSI Approved :: Apache Software License
Classifier: Programming Language :: Python :: 2
Classifier: Programming Language :: Python :: 2.7
Classifier: Programming Language :: Python :: 3
Classifier: Programming Language :: Python :: 3.4
Classifier: Programming Language :: Python :: 3.5
Classifier: Programming Language :: Python :: 3.6
Classifier: Programming Language :: Python :: 3.7
